e_chem/__init__.py
e_chem/cp.py
e_chem/cv.py
e_chem/ecsa.py
e_chem/peis.py
e_chem/tafel.py
e_chem-1.0.1.dist-info/METADATA
e_chem-1.0.1.dist-info/WHEEL
e_chem-1.0.1.dist-info/top_level.txt
e_chem-1.0.1.dist-info/RECORD
