Metadata-Version: 2.4
Name: e-chem
Version: 1.0.1
Summary: echemkit is a lightweight Python library designed for seamless electrochemical data analysis.
Home-page: https://gitlab.tuwien.ac.at/iap/aip/anp/electrochemistry/basic-ec/e-chem
Author: Nico Sonderhof, Lorenz Unterberger, Richard W. van Nieuwenhoven, Markus Valtiner
Author-email: nico.sonderhof@tuwien.ac.at
Project-URL: Homepage, https://researchdata.tuwien.ac.at/uploads/4exfe-yx784
Keywords: todo
Classifier: Programming Language :: Python :: 3
Classifier: License :: OSI Approved :: MIT License
Classifier: Operating System :: OS Independent
Requires-Python: >=3.1
Requires-Dist: matplotlib>=3.5.1
Requires-Dist: NumPy>=1.26
Requires-Dist: pandas>=2.2.3
Requires-Dist: scipy>=1.15.3
Dynamic: author
Dynamic: author-email
Dynamic: classifier
Dynamic: description
Dynamic: description-content-type
Dynamic: home-page
Dynamic: keywords
Dynamic: project-url
Dynamic: requires-dist
Dynamic: requires-python
Dynamic: summary
